path_toolkit-0.2.1.dist-info/METADATA
path_toolkit-0.2.1.dist-info/WHEEL
path_toolkit-0.2.1.dist-info/licenses/LICENSE
path_toolkit.libs/libopenblas-f650aae0.so.0
path_toolkit.libs/libgfortran-91cc3cb1.so.3
path_toolkit.libs/libquadmath-96973f99.so.0
path_toolkit/__init__.py
path_toolkit/path_toolkit.cpython-310-x86_64-linux-gnu.so
path_toolkit-0.2.1.dist-info/RECORD
