Metadata-Version: 2.3
Name: path_toolkit
Version: 0.2.1
Classifier: Programming Language :: Rust
Classifier: Programming Language :: Python :: Implementation :: CPython
Classifier: Programming Language :: Python :: Implementation :: PyPy
License-File: LICENSE
Summary: Useful functions for working with paths
Author-email: Kilian Northoff <kilian.northoff@tum.de>
License: MIT License
Requires-Python: >=3.8, <=3.12
Project-URL: Repository, https://github.com/Deepthought73/path_toolkit.git
